CHANGELOG
LICENSE.txt
MANIFEST.in
README
setup.py
chemfp_converters/__init__.py
chemfp_converters/cmdsupport.py
chemfp_converters/fastsearch.py
chemfp_converters/flush.py
chemfp_converters/flush2fps.py
chemfp_converters/fpbin.py
chemfp_converters/fpbin2fps.py
chemfp_converters/fps2flush.py
chemfp_converters/fps2fpbin.py
chemfp_converters/fps2fs.py
chemfp_converters/fs2fps.py
chemfp_converters.egg-info/PKG-INFO
chemfp_converters.egg-info/SOURCES.txt
chemfp_converters.egg-info/dependency_links.txt
chemfp_converters.egg-info/entry_points.txt
chemfp_converters.egg-info/requires.txt
chemfp_converters.egg-info/top_level.txt
tests/drugs.flush
tests/drugs.fpbin
tests/drugs.fs
tests/drugs.sdf
tests/drugs_openbabel_FP2.fps
tests/drugs_openeye_path.fps
tests/support.py
tests/test_fastsearch.py
tests/test_flush.py
tests/test_fpbin.py
tests/unit2
tests/vitamins.flush
tests/vitamins.fpbin
tests/vitamins.fs
tests/vitamins.smi
tests/vitamins_openbabel_MACCS.fps
tests/vitamins_openeye_circular.fps
tests/vitamins_rdkit_Morgan.fps
tests/vitamins_tab.smi.gz