Metadata-Version: 1.1
Name: chemfp-converters
Version: 0.9.1
Summary: Convert cheminformatics fingerprint files to/from the chemfp formats
Home-page: https://bitbucket.org/dalke/chemfp_converters
Author: Andrew Dalke
Author-email: dalke@dalkescientific.com
License: MIT
Keywords: chemfp cheminformatics fingerprint converter FPS FPB
Platform: UNKNOWN
Classifier: Development Status :: 4 - Beta
Classifier: Intended Audience :: Science/Research
Classifier: License :: OSI Approved :: MIT License
Classifier: Operating System :: Unix
Classifier: Programming Language :: Python :: 2.7
Classifier: Programming Language :: Python :: 3
Classifier: Topic :: Scientific/Engineering :: Chemistry
